[{
	"categories": [
		{
			"id": 1,
			"name": "Travel"
		}, {
			"id": 2,
			"name": "Mystery"
		}, {
			"id": 3,
			"name": "Historical Fiction"
		}
	],
	"books": [
		{
			"id": 1,
			"category_id": 1,
			"title": "It's Only the Himalayas",
			"thumbnail_url": "http://books.toscrape.com/media/cache/6d/41/6d418a73cc7d4ecfd75ca11d854041db.jpg",
			"price": "£45.17",
			"stock": true,
			"product_description": "Wherever you go, whatever you do, just ...",
			"upc": "a22124811bfa8350"
		},
	],
}]
